{
    "chain_name": "stargaze",
    "api": ["https://rest.stargaze-apis.com", "https://rest.stargaze.publicawesome.dev"],
    "rpc": ["https://rpc.stargaze-apis.com:443", "https://rpc.stargaze.ezstaking.io:443"],
    "snapshot_provider": "",
    "sdk_version": "0.44.3",
    "coin_type": "118",
    "min_tx_fee": "800",
    "addr_prefix": "stars",
    "logo": "/logos/stargaze.png",
    "assets": [{
        "base": "ustars",
        "symbol": "STARS",
        "exponent": "6",
        "coingecko_id": "stargaze", 
        "logo": "/logos/stargaze.png"
    }]
}