{
  "chain_name": "xion-mainnet-1",
  "coingecko": "XION",
  "network_type": "mainnet",
  "rpc": [
    {
      "address": "https://rpc.xion-mainnet-1.burnt.com",
      "provider": "🔥BurntLabs🔥"
    },
    {
      "address": "https://xion-rpc.lavenderfive.com",
      "provider": "Lavender.Five Nodes 🐝"
    },
    {
      "address": "https://rpc-burnt.imperator.co/",
      "provider": "Imperator.co"
    },
    {
      "address": "https://xion-rpc.polkachu.com",
      "provider": "Polkachu"
    },
    {
      "address": "https://xion-rpc.kingnodes.com",
      "provider": "Kingnodes \ud83d\udc51"
    }
  ],
  "api": [
    {
      "address": "https://api.xion-mainnet-1.burnt.com",
      "provider": "🔥BurntLabs🔥"
    },
    {
      "address": "https://xion-api.lavenderfive.com",
      "provider": "Lavender.Five Nodes 🐝"
    },
    {
      "address": "https://lcd-burnt.imperator.co/",
      "provider": "Imperator.co"
    },
    {
      "address": "https://xion-api.polkachu.com",
      "provider": "Polkachu"
    },
    {
      "address": "https://xion-rest.kingnodes.com",
      "provider": "Kingnodes \ud83d\udc51"
    }
  ],
  "snapshot_provider": "",
  "sdk_version": "0.50.13",
  "coin_type": "118",
  "min_tx_fee": "100",
  "addr_prefix": "xion",
  "logo": "https://raw.githubusercontent.com/cosmos/chain-registry/master/xion/images/burnt-round.png",
  "assets": [
    {
      "base": "uxion",
      "symbol": "XION",
      "exponent": "6",
      "coingecko_id": "xion-2",
      "logo": "https://raw.githubusercontent.com/cosmos/chain-registry/master/xion/images/burnt-round.png"
    },
    {
      "base": "ibc/0471F1C4E7AFD3F07702BEF6DC365268D64570F7C1FDC98EA6098DD6DE59817B",
      "symbol": "OSMO",
      "exponent": "6",
      "coingecko_id": "osmosis",
      "logo": "https://raw.githubusercontent.com/cosmos/chain-registry/master/osmosis/images/osmo.png"
    },
    {
      "base": "ibc/CC7B293B3F08EA7DB96AFD4765BD0C7F95ABD7ECEAF21C74F3ACCBF7CEFB6591",
      "symbol": "OSMO",
      "exponent": "6",
      "coingecko_id": "osmosis",
      "logo": "https://raw.githubusercontent.com/cosmos/chain-registry/master/osmosis/images/osmo.png"
    },
    {
      "base": "ibc/F082B65C88E4B6D5EF1DB243CDA1D331D002759E938A0F5CD3FFDC5D53B3E349",
      "symbol": "USDC",
      "exponent": "6",
      "coingecko_id": "usd-coin",
      "logo": "https://raw.githubusercontent.com/cosmos/chain-registry/master/noble/images/USDCoin.png"
    }
  ],
  "keplr_features": [
    "ibc-go",
    "ibc-transfer",
    "no-legacy-stdTx"
  ]
}
